Metadata-Version: 2.1
Name: uniqpy
Version: 0.1.3
Summary: UNIQUAC-based tool for multicomponent VLEs
Home-page: https://github.com/DNKonanov/uni_cli
Author: D.N. Konanov
Author-email: konanovdmitriy@gmail.com
License: UNKNOWN
Project-URL: Bug Tracker, https://github.com/DNKonanov/uni_cli
Platform: UNKNOWN
Classifier: Programming Language :: Python :: 3
Classifier: License :: OSI Approved :: MIT License
Classifier: Operating System :: OS Independent
Requires-Python: >=3.7
License-File: LICENSE
